Lab1/bcdtogray_tb.v
module testbench();
    reg [0:3] inp;
    wire [0:3] gray;

    bcdtogray_df bcdtogray(inp, gray);
    initial
        begin
            $monitor(, $time, " input = %b,  gray = %b", inp, gray);
            #0 inp = 4'b0000;
            #5 inp = 4'b0001;
            #5 inp = 4'b0010;
            #5 inp = 4'b0011;
            #5 inp = 4'b0100;
            #5 inp = 4'b0101;
            #5 inp = 4'b0110;
            #5 inp = 4'b0111;
            #5 inp = 4'b1000;
            #5 inp = 4'b1001;
            #10 $finish;
        end
    initial
        begin
            $dumpfile("output.vcd");
            $dumpvars();
        end
endmodule

Lab1/bcdtogray.v
module bcdtogray_df (inp, gray);
    input [0:3] inp;
    output [0:3] gray;

    assign gray[0] = inp[0];
    assign gray[1] = inp[0] ^ inp[1];
    assign gray[2] = inp[1] ^ inp[2];
    assign gray[3] = inp[2] ^ inp[3];
endmodule

module bcdtogray_gl (inp, gray);
    input [0:3] inp;
    output [0:3] gray;

    buf(gray[0], inp[0]);
    xor(gray[1], inp[0], inp[1]);
    xor(gray[2], inp[1], inp[2]);
    xor(gray[3], inp[2], inp[3]);
endmodule

Lab1/output.vcd
$date
	Tue Nov 13 19:07:48 2018
$end
$version
	Icarus Verilog
$end
$timescale
	1s
$end
$scope module bcdtogray_gl $end
$var wire 4 ! gray [0:3] $end
$var wire 4 " inp [0:3] $end
$upscope $end
$scope module testbench $end
$var wire 4 # gray [0:3] $end
$var reg 4 $ inp [0:3] $end
$scope module bcdtogray $end
$var wire 4 % gray [0:3] $end
$var wire 4 & inp [0:3] $end
$upscope $end
$upscope $end
$enddefinitions $end
#0
$dumpvars
b0 &
b0 %
b0 $
b0 #
bz "
bx !
$end
#5
b1 #
b1 %
b1 $
b1 &
#10
b11 #
b11 %
b10 $
b10 &
#15
b10 #
b10 %
b11 $
b11 &
#20
b110 #
b110 %
b100 $
b100 &
#25
b111 #
b111 %
b101 $
b101 &
#30
b101 #
b101 %
b110 $
b110 &
#35
b100 #
b100 %
b111 $
b111 &
#40
b1100 #
b1100 %
b1000 $
b1000 &
#45
b1101 #
b1101 %
b1001 $
b1001 &
