Lab2/fullAdderBehavior.v
module fadderbh(s, c, x, y, z);
    input x, y, z;
    output s, c;
    reg s, c;

    always @(x, y, z)
    begin
        if(x + y + z == 3)
        begin
            s = 1; c = 1;
        end
        else if(x + y + z == 2)
        begin
            s = 0; c = 1;
        end
        else if(x + y + z == 1)
        begin
            s = 1; c = 0; 
        end
        else
        begin
            s = 0; c = 0;
        end
    end

endmodule

Lab2/addSub.v
module ADDSUB(a, b, m, answer, v, finalcarry);
    
    input [0:3] a;
    input [0:3] b;
    input m;
    output [0:3] answer;
    output v;
    output finalcarry;
    wire transformedB[0:3];
    wire intermediatecarrys[0:3];

    assign transformedB[0] = m ^ b[0];
    assign transformedB[1] = m ^ b[1];
    assign transformedB[2] = m ^ b[2];
    assign transformedB[3] = m ^ b[3];

    fadderbh f1(answer[3], intermediatecarrys[0], a[3], transformedB[3], m);
    fadderbh f2(answer[2], intermediatecarrys[1], a[2], transformedB[2], intermediatecarrys[0]);
    fadderbh f3(answer[1], intermediatecarrys[2], a[1], transformedB[1], intermediatecarrys[1]);
    fadderbh f4(answer[0], finalcarry, a[0], transformedB[0], intermediatecarrys[2]);

    assign v = finalcarry ^ intermediatecarrys[2];

endmodule

Lab2/addSub_tb.v
module testbench;
    reg [0:3] a;
    reg [0:3] b;
    reg m;
    wire [0:3] answer;
    wire overflow;
    wire finalcarry;
    ADDSUB addsub(a, b, m, answer, overflow, finalcarry);

    initial
        begin
            $monitor(, "a = %b, b = %b, control = %b, answer = %b, overflow = %b, carryout = %b", a, b, m, answer, overflow, finalcarry);
            #0 a = 4'b0011; b = 4'b1001; m = 0;
            #5 a = 4'b0011; b = 4'b1001; m = 1;
            #5 a = 4'b1001; b = 4'b1001; m = 0;
            #5 a = 4'b1001; b = 4'b1001; m = 1;
            #5 a = 4'b1111; b = 4'b0011; m = 0;
            #5 a = 4'b1111; b = 4'b0011; m = 1;
            #5 a = 4'b1110; b = 4'b0111; m = 0;
            #5 a = 4'b1110; b = 4'b0111; m = 1;
            #5 $finish;
        end
    initial
        begin
            $dumpfile("output.vcd");
            $dumpvars();  
        end
endmodule

Lab2/output.vcd
$date
	Tue Nov 13 23:41:38 2018
$end
$version
	Icarus Verilog
$end
$timescale
	1s
$end
$scope module testbench $end
$var wire 4 ! answer [0:3] $end
$var wire 1 " finalcarry $end
$var wire 1 # overflow $end
$var reg 4 $ a [0:3] $end
$var reg 4 % b [0:3] $end
$var reg 1 & m $end
$scope module addsub $end
$var wire 4 ' a [0:3] $end
$var wire 4 ( answer [0:3] $end
$var wire 4 ) b [0:3] $end
$var wire 1 " finalcarry $end
$var wire 1 * m $end
$var wire 1 # v $end
$scope module f1 $end
$var wire 1 + x $end
$var wire 1 , y $end
$var wire 1 * z $end
$var reg 1 - c $end
$var reg 1 . s $end
$upscope $end
$scope module f2 $end
$var wire 1 / x $end
$var wire 1 0 y $end
$var wire 1 1 z $end
$var reg 1 2 c $end
$var reg 1 3 s $end
$upscope $end
$scope module f3 $end
$var wire 1 4 x $end
$var wire 1 5 y $end
$var wire 1 6 z $end
$var reg 1 7 c $end
$var reg 1 8 s $end
$upscope $end
$scope module f4 $end
$var wire 1 9 x $end
$var wire 1 : y $end
$var wire 1 ; z $end
$var reg 1 < c $end
$var reg 1 = s $end
$upscope $end
$upscope $end
$upscope $end
$enddefinitions $end
#0
$dumpvars
1=
0<
0;
1:
09
18
07
16
05
04
03
12
11
00
1/
0.
1-
1,
1+
0*
b1001 )
b1100 (
b11 '
0&
b1001 %
b11 $
0#
0"
b1100 !
$end
#5
1#
17
1;
08
13
0:
15
10
0,
0.
b1010 !
b1010 (
1&
1*
#10
0=
07
0;
02
06
13
1<
1"
1:
05
00
1,
1-
11
0.
b10 !
b10 (
0/
19
0&
0*
b1001 $
b1001 '
#15
0#
17
1;
12
16
03
0:
15
10
0,
0.
b0 !
b0 (
1&
1*
#20
13
05
1,
1-
11
0.
b10 !
b10 (
1/
14
0&
0*
b11 %
b11 )
b1111 $
b1111 '
#25
1=
18
03
1:
15
00
0,
0.
b1100 !
b1100 (
1&
1*
#30
0=
1.
b101 !
b101 (
0:
10
1,
0-
01
0+
0&
0*
b111 %
b111 )
b1110 $
b1110 '
#35
1#
07
0;
02
06
13
0=
18
1:
05
00
0,
0-
01
1.
b111 !
b111 (
1&
1*
