Lab2/4to1mux_gl.v
module mux4to1_gate(out,in,sel);
    input [0:3] in;
    input [1:0] sel;
    output out;

    wire n0, n1, a1, a2, a3, a4;
    
    not (n0, sel[0]);
    not (n1, sel[1]);

    and A1(a1, in[0], n0, n1);
    and A2(a2, in[1], n1, sel[0]);
    and A3(a3, in[2], sel[1], n0);
    and A4(a4, in[3], sel[1], sel[0]);

    or O1(out, a1, a2, a3, a4);

endmodule

Lab2/16to1mux_gl.v
module mux16to1(out,in,sel);
    input [0:15] in;
    input [0:3] sel;

    output out;

    wire [0:3] intermediate;

    mux4to1_gate m0(intermediate[0], in[0:3], sel[2:3]);
    mux4to1_gate m1(intermediate[1], in[4:7], sel[2:3]);
    mux4to1_gate m2(intermediate[2], in[8:11], sel[2:3]);
    mux4to1_gate m3(intermediate[3], in[12:15], sel[2:3]);

    mux4to1_gate m4(out, intermediate, sel[0:1]);
endmodule

Lab2/16to1mux_gl_tb.v
module testbench();
    reg [0:15] inp;
    reg [0:3] sel;
    wire out;

    mux16to1 myMux(out, inp, sel);

    initial
        begin
            $monitor(, $time, " inp = %b, sel = %b, out = %b", inp, sel, out);
            #3 inp=16'b0010000000000000; sel=4'b0010;
            #3 inp=16'b0001000000000000; sel=4'b0011;
            #3 inp=16'b0000100000000000; sel=4'b0100;
            #3 inp=16'b0000010000000000; sel=4'b0101;
            #3 inp=16'b0000001000000000; sel=4'b0110;
            #3 inp=16'b0000000100000000; sel=4'b0111;
            #3 inp=16'b0000000010000000; sel=4'b1000;
            #3 inp=16'b0000000001000000; sel=4'b1001;
            #3 inp=16'b0000000000100000; sel=4'b1010;
            #3 inp=16'b0000000000010000; sel=4'b1011;
            #3 inp=16'b0000000000001000; sel=4'b1100;
            #3 inp=16'b0000000000000100; sel=4'b1101;
            #3 inp=16'b0000000000000010; sel=4'b1110;
            #3 inp=16'b0000000000000001; sel=4'b1111;
            #3 $finish;
        end
    initial
        begin
            $dumpfile("output.vcd");
            $dumpvars(); 
        end
endmodule

Lab2/output.vcd
$date
	Tue Nov 13 21:24:13 2018
$end
$version
	Icarus Verilog
$end
$timescale
	1s
$end
$scope module testbench $end
$var wire 1 ! out $end
$var reg 16 " inp [0:15] $end
$var reg 4 # sel [0:3] $end
$scope module myMux $end
$var wire 16 $ in [0:15] $end
$var wire 4 % intermediate [0:3] $end
$var wire 1 ! out $end
$var wire 4 & sel [0:3] $end
$scope module m0 $end
$var wire 1 ' a1 $end
$var wire 1 ( a2 $end
$var wire 1 ) a3 $end
$var wire 1 * a4 $end
$var wire 4 + in [0:3] $end
$var wire 1 , n0 $end
$var wire 1 - n1 $end
$var wire 1 . out $end
$var wire 2 / sel [1:0] $end
$upscope $end
$scope module m1 $end
$var wire 1 0 a1 $end
$var wire 1 1 a2 $end
$var wire 1 2 a3 $end
$var wire 1 3 a4 $end
$var wire 4 4 in [0:3] $end
$var wire 1 5 n0 $end
$var wire 1 6 n1 $end
$var wire 1 7 out $end
$var wire 2 8 sel [1:0] $end
$upscope $end
$scope module m2 $end
$var wire 1 9 a1 $end
$var wire 1 : a2 $end
$var wire 1 ; a3 $end
$var wire 1 < a4 $end
$var wire 4 = in [0:3] $end
$var wire 1 > n0 $end
$var wire 1 ? n1 $end
$var wire 1 @ out $end
$var wire 2 A sel [1:0] $end
$upscope $end
$scope module m3 $end
$var wire 1 B a1 $end
$var wire 1 C a2 $end
$var wire 1 D a3 $end
$var wire 1 E a4 $end
$var wire 4 F in [0:3] $end
$var wire 1 G n0 $end
$var wire 1 H n1 $end
$var wire 1 I out $end
$var wire 2 J sel [1:0] $end
$upscope $end
$scope module m4 $end
$var wire 1 K a1 $end
$var wire 1 L a2 $end
$var wire 1 M a3 $end
$var wire 1 N a4 $end
$var wire 4 O in [0:3] $end
$var wire 1 P n0 $end
$var wire 1 Q n1 $end
$var wire 1 ! out $end
$var wire 2 R sel [1:0] $end
$upscope $end
$upscope $end
$upscope $end
$enddefinitions $end
#0
$dumpvars
bx R
xQ
xP
bz O
xN
xM
xL
xK
bx J
zI
xH
xG
bx F
xE
xD
xC
xB
bx A
z@
x?
x>
bx =
x<
x;
x:
x9
bx 8
z7
x6
x5
bx 4
x3
x2
x1
x0
bx /
z.
x-
x,
bx +
x*
x)
x(
x'
bx &
bz %
bx $
bx #
bx "
z!
$end
#3
1K
1)
1!
1.
07
0@
0I
b1000 %
b1000 O
1,
0-
15
06
1>
0?
1G
0H
1P
1Q
0L
0M
0N
0'
0(
0*
00
01
02
03
09
0:
0;
0<
0B
0C
0D
0E
b10 /
b10 8
b10 A
b10 J
b0 R
b10 +
b0 4
b0 =
b0 F
b10 #
b10 &
b10000000000000 "
b10000000000000 $
#6
0,
05
0>
0G
0)
1*
b11 /
b11 8
b11 A
b11 J
b1 +
b11 #
b11 &
b1000000000000 "
b1000000000000 $
#9
1L
17
1!
10
0K
0.
b100 %
b100 O
1,
1-
15
16
1>
1?
1G
1H
0P
0*
b0 /
b0 8
b0 A
b0 J
b1 R
b0 +
b1000 4
b100 #
b100 &
b100000000000 "
b100000000000 $
#12
0,
05
0>
0G
00
11
b1 /
b1 8
b1 A
b1 J
b100 4
b101 #
b101 &
b10000000000 "
b10000000000 $
#15
1!
1L
12
17
b100 %
b100 O
1,
0-
15
06
1>
0?
1G
0H
01
b10 /
b10 8
b10 A
b10 J
b10 4
b110 #
b110 &
b1000000000 "
b1000000000 $
#18
0,
05
0>
0G
02
13
b11 /
b11 8
b11 A
b11 J
b1 4
b111 #
b111 &
b100000000 "
b100000000 $
#21
1M
1@
19
1!
07
b10 %
b10 O
1,
1-
15
16
1>
1?
1G
1H
1P
0Q
0L
03
b0 /
b0 8
b0 A
b0 J
b10 R
b0 4
b1000 =
b1000 #
b1000 &
b10000000 "
b10000000 $
#24
0,
05
0>
0G
09
1:
b1 /
b1 8
b1 A
b1 J
b100 =
b1001 #
b1001 &
b1000000 "
b1000000 $
#27
1!
1M
1;
1@
b10 %
b10 O
1,
0-
15
06
1>
0?
1G
0H
0:
b10 /
b10 8
b10 A
b10 J
b10 =
b1010 #
b1010 &
b100000 "
b100000 $
#30
0,
05
0>
0G
0;
1<
b11 /
b11 8
b11 A
b11 J
b1 =
b1011 #
b1011 &
b10000 "
b10000 $
#33
1N
1I
1!
1B
0M
0@
b1 %
b1 O
1,
1-
15
16
1>
1?
1G
1H
0P
0<
b0 /
b0 8
b0 A
b0 J
b11 R
b0 =
b1000 F
b1100 #
b1100 &
b1000 "
b1000 $
#36
0,
05
0>
0G
0B
1C
b1 /
b1 8
b1 A
b1 J
b100 F
b1101 #
b1101 &
b100 "
b100 $
#39
1!
1N
1D
1I
b1 %
b1 O
1,
0-
15
06
1>
0?
1G
0H
0C
b10 /
b10 8
b10 A
b10 J
b10 F
b1110 #
b1110 &
b10 "
b10 $
#42
0,
05
0>
0G
0D
1E
b11 /
b11 8
b11 A
b11 J
b1 F
b1111 #
b1111 &
b1 "
b1 $
